tpnetwork/__init__.py
tpnetwork/network/__init__.py
tpnetwork/network/ipv4/__init__.py
tpnetwork/network/ipv4/address.py
tpnetwork/network/ipv4/exceptions.py
tpnetwork/network/ipv4/network.py
tpnetwork-1.1.3.dist-info/LICENSE
tpnetwork-1.1.3.dist-info/METADATA
tpnetwork-1.1.3.dist-info/WHEEL
tpnetwork-1.1.3.dist-info/top_level.txt
tpnetwork-1.1.3.dist-info/RECORD
