Metadata-Version: 2.1
Name: tpnetwork
Version: 1.1.3
Summary: A python network module
Home-page: https://github.com/tomarrok/tpnetwork
Author: Thomas Pajon
Author-email: th.pajon45@gmail.com
License: UNKNOWN
Platform: UNKNOWN
Classifier: Programming Language :: Python :: 3.7
Classifier: Development Status :: 5 - Production/Stable
Classifier: Intended Audience :: Developers
Classifier: Topic :: System :: Networking
Classifier: License :: OSI Approved :: MIT License
Classifier: Operating System :: Unix
Classifier: Natural Language :: English
Requires-Python: >=3.5
